geomio/__init__.py
geomio-0.0.1.dist-info/licenses/LICENSE
geomio-0.0.1.dist-info/METADATA
geomio-0.0.1.dist-info/WHEEL
geomio-0.0.1.dist-info/top_level.txt
geomio-0.0.1.dist-info/RECORD
