Metadata-Version: 2.4
Name: geomio
Version: 0.0.1
Summary: Geometry Analysis, Operations, and Management for GeoPackages
Author-email: "Integrated Informatics (USA) Inc." <contact@integrated-informatics.com>
License-Expression: MIT
Keywords: geopackage,geometry,gis,spatial,analysis
Classifier: Programming Language :: Python
Classifier: Programming Language :: Python :: 3
Classifier: Programming Language :: Python :: 3.11
Classifier: Programming Language :: Python :: 3.12
Classifier: Programming Language :: Python :: 3.13
Classifier: Programming Language :: Python :: 3.14
Classifier: Operating System :: OS Independent
Requires-Python: >=3.11
License-File: LICENSE
Dynamic: license-file
